gitatp/__init__.py
gitatp/__main__.py
gitatp/cli.py
gitatp/git_http_backend.py
gitatp/update_profile.js
gitatp-0.5.0.dist-info/METADATA
gitatp-0.5.0.dist-info/WHEEL
gitatp-0.5.0.dist-info/entry_points.txt
gitatp-0.5.0.dist-info/licenses/LICENSE
gitatp-0.5.0.dist-info/RECORD
