Metadata-Version: 2.3
Name: gitatp
Version: 0.5.0
Summary: Git over ATProto
Project-URL: Repository, https://github.com/publicdomainrelay/gitatp.git
Project-URL: Issues, https://github.com/publicdomainrelay/gitatp/issues
Author-email: Public Domain <publicdomainrelay@protonmail.com>
License: Unlicense
Requires-Python: >=3.12
Requires-Dist: aiohttp-asgi>=0.5.2
Requires-Dist: atproto>=0.0.55
Requires-Dist: fastapi>=0.115.5
Requires-Dist: fastui>=0.7.0
Requires-Dist: keyring>=25.5.0
Requires-Dist: markdown2>=2.5.1
Requires-Dist: pydantic>=2.10.2
Requires-Dist: pygments>=2.18.0
Requires-Dist: python-magic>=0.4.27
Requires-Dist: snoop>=0.6.0
